setup.py
Marine_AI/__init__.py
Marine_AI/evaluate.py
Marine_AI/util.py
Marine_AI.egg-info/PKG-INFO
Marine_AI.egg-info/SOURCES.txt
Marine_AI.egg-info/dependency_links.txt
Marine_AI.egg-info/top_level.txt