Metadata-Version: 2.1
Name: Marine-AI
Version: 0.0.5
Summary: Combination of ocean and deep learning
Home-page: https://github.com/
License: UNKNOWN
Platform: UNKNOWN
Classifier: Programming Language :: Python :: 3
Classifier: License :: OSI Approved :: MIT License
Classifier: Operating System :: OS Independent
